libdnb/__init__.py
libdnb-0.0.1.dist-info/LICENSE
libdnb-0.0.1.dist-info/METADATA
libdnb-0.0.1.dist-info/WHEEL
libdnb-0.0.1.dist-info/top_level.txt
libdnb-0.0.1.dist-info/RECORD
