Metadata-Version: 2.1
Name: libdnb
Version: 0.0.1
Summary: German National library api
Home-page: https://github.com/nerrixDE/libdnb
Author: nerrixDE
Author-email: nerrixde@mailfence.com
License: UNKNOWN
Platform: UNKNOWN
Classifier: Programming Language :: Python :: 3
Classifier: License :: OSI Approved :: GNU General Public License v3 (GPLv3)
Classifier: Operating System :: OS Independent
Requires-Python: >=3.5
